{
  "userId": "eng-014",
  "name": "Nancy Huang",
  "createdAt": "2026-01-05T00:00:00Z",
  "lastScannedAt": "2026-02-13T08:00:00Z",
  "roadmaps": {
    "role:Data Engineer": {
      "roadmapVersion": "1.0",
      "firstUnlockedAt": "2026-01-06T08:00:00Z",
      "lastActivityAt": "2026-02-11T08:00:00Z",
      "completions": {
        "py-basics": {
          "firstDetectedAt": "2026-01-06T08:00:00Z",
          "lastDetectedAt": "2026-01-27T08:00:00Z",
          "detectionCount": 27
        },
        "sql-advanced": {
          "firstDetectedAt": "2026-01-18T08:00:00Z",
          "lastDetectedAt": "2026-02-10T08:00:00Z",
          "detectionCount": 31
        },
        "py-db-connect": {
          "firstDetectedAt": "2026-01-09T08:00:00Z",
          "lastDetectedAt": "2026-01-26T08:00:00Z",
          "detectionCount": 35
        },
        "db-normalization": {
          "firstDetectedAt": "2026-01-06T08:00:00Z",
          "lastDetectedAt": "2026-01-19T08:00:00Z",
          "detectionCount": 36
        },
        "db-indexing": {
          "firstDetectedAt": "2026-01-28T08:00:00Z",
          "lastDetectedAt": "2026-02-03T08:00:00Z",
          "detectionCount": 34
        },
        "db-constraints": {
          "firstDetectedAt": "2026-01-23T08:00:00Z",
          "lastDetectedAt": "2026-02-08T08:00:00Z",
          "detectionCount": 37
        },
        "etl-concepts": {
          "firstDetectedAt": "2026-01-28T08:00:00Z",
          "lastDetectedAt": "2026-01-29T08:00:00Z",
          "detectionCount": 37
        },
        "etl-tools": {
          "firstDetectedAt": "2026-01-10T08:00:00Z",
          "lastDetectedAt": "2026-01-18T08:00:00Z",
          "detectionCount": 26
        },
        "dw-concepts": {
          "firstDetectedAt": "2026-01-20T08:00:00Z",
          "lastDetectedAt": "2026-02-06T08:00:00Z",
          "detectionCount": 37
        },
        "dw-snowflake": {
          "firstDetectedAt": "2026-01-12T08:00:00Z",
          "lastDetectedAt": "2026-01-24T08:00:00Z",
          "detectionCount": 35
        },
        "dw-bigquery": {
          "firstDetectedAt": "2026-01-14T08:00:00Z",
          "lastDetectedAt": "2026-02-09T08:00:00Z",
          "detectionCount": 22
        },
        "dw-redshift": {
          "firstDetectedAt": "2026-01-24T08:00:00Z",
          "lastDetectedAt": "2026-02-09T08:00:00Z",
          "detectionCount": 23
        },
        "spark-rdd-df": {
          "firstDetectedAt": "2026-01-07T08:00:00Z",
          "lastDetectedAt": "2026-01-18T08:00:00Z",
          "detectionCount": 29
        },
        "spark-optimization": {
          "firstDetectedAt": "2026-01-20T08:00:00Z",
          "lastDetectedAt": "2026-02-01T08:00:00Z",
          "detectionCount": 20
        },
        "spark-pyspark": {
          "firstDetectedAt": "2026-01-09T08:00:00Z",
          "lastDetectedAt": "2026-01-26T08:00:00Z",
          "detectionCount": 38
        },
        "model-star-schema": {
          "firstDetectedAt": "2026-01-10T08:00:00Z",
          "lastDetectedAt": "2026-02-11T08:00:00Z",
          "detectionCount": 29
        },
        "kafka-topics": {
          "firstDetectedAt": "2026-01-12T08:00:00Z",
          "lastDetectedAt": "2026-02-10T08:00:00Z",
          "detectionCount": 24
        },
        "kafka-producers": {
          "firstDetectedAt": "2026-01-15T08:00:00Z",
          "lastDetectedAt": "2026-02-09T08:00:00Z",
          "detectionCount": 35
        },
        "kafka-streams": {
          "firstDetectedAt": "2026-01-12T08:00:00Z",
          "lastDetectedAt": "2026-02-11T08:00:00Z",
          "detectionCount": 34
        }
      }
    },
    "role:Data Analyst": {
      "roadmapVersion": "1.0",
      "firstUnlockedAt": "2026-01-08T08:00:00Z",
      "lastActivityAt": "2026-02-11T08:00:00Z",
      "completions": {
        "sheets-formulas": {
          "firstDetectedAt": "2026-01-19T08:00:00Z",
          "lastDetectedAt": "2026-01-19T08:00:00Z",
          "detectionCount": 15
        },
        "sheets-pivot-tables": {
          "firstDetectedAt": "2026-01-11T08:00:00Z",
          "lastDetectedAt": "2026-01-20T08:00:00Z",
          "detectionCount": 18
        },
        "sheets-charts": {
          "firstDetectedAt": "2026-01-11T08:00:00Z",
          "lastDetectedAt": "2026-02-11T08:00:00Z",
          "detectionCount": 12
        },
        "sheets-data-validation": {
          "firstDetectedAt": "2026-01-18T08:00:00Z",
          "lastDetectedAt": "2026-02-07T08:00:00Z",
          "detectionCount": 8
        },
        "sql-select": {
          "firstDetectedAt": "2026-01-11T08:00:00Z",
          "lastDetectedAt": "2026-01-27T08:00:00Z",
          "detectionCount": 15
        },
        "sql-joins": {
          "firstDetectedAt": "2026-01-15T08:00:00Z",
          "lastDetectedAt": "2026-01-15T08:00:00Z",
          "detectionCount": 17
        },
        "sql-aggregation": {
          "firstDetectedAt": "2026-01-21T08:00:00Z",
          "lastDetectedAt": "2026-02-02T08:00:00Z",
          "detectionCount": 8
        },
        "sql-subqueries": {
          "firstDetectedAt": "2026-01-09T08:00:00Z",
          "lastDetectedAt": "2026-01-29T08:00:00Z",
          "detectionCount": 10
        },
        "stats-descriptive": {
          "firstDetectedAt": "2026-01-21T08:00:00Z",
          "lastDetectedAt": "2026-02-08T08:00:00Z",
          "detectionCount": 12
        },
        "viz-design": {
          "firstDetectedAt": "2026-01-08T08:00:00Z",
          "lastDetectedAt": "2026-02-01T08:00:00Z",
          "detectionCount": 15
        },
        "viz-tableau": {
          "firstDetectedAt": "2026-01-27T08:00:00Z",
          "lastDetectedAt": "2026-02-10T08:00:00Z",
          "detectionCount": 13
        },
        "viz-powerbi": {
          "firstDetectedAt": "2026-01-24T08:00:00Z",
          "lastDetectedAt": "2026-01-29T08:00:00Z",
          "detectionCount": 12
        },
        "py-pandas": {
          "firstDetectedAt": "2026-01-08T08:00:00Z",
          "lastDetectedAt": "2026-02-02T08:00:00Z",
          "detectionCount": 10
        }
      }
    },
    "skill:Python": {
      "roadmapVersion": "1.0",
      "firstUnlockedAt": "2026-01-06T08:00:00Z",
      "lastActivityAt": "2026-02-10T08:00:00Z",
      "completions": {
        "variables-types": {
          "firstDetectedAt": "2026-01-17T08:00:00Z",
          "lastDetectedAt": "2026-02-08T08:00:00Z",
          "detectionCount": 24
        },
        "control-flow": {
          "firstDetectedAt": "2026-01-06T08:00:00Z",
          "lastDetectedAt": "2026-01-07T08:00:00Z",
          "detectionCount": 28
        },
        "functions": {
          "firstDetectedAt": "2026-01-12T08:00:00Z",
          "lastDetectedAt": "2026-01-26T08:00:00Z",
          "detectionCount": 35
        },
        "input-output": {
          "firstDetectedAt": "2026-01-16T08:00:00Z",
          "lastDetectedAt": "2026-02-10T08:00:00Z",
          "detectionCount": 35
        },
        "lists-tuples": {
          "firstDetectedAt": "2026-01-07T08:00:00Z",
          "lastDetectedAt": "2026-01-22T08:00:00Z",
          "detectionCount": 23
        },
        "dicts-sets": {
          "firstDetectedAt": "2026-01-23T08:00:00Z",
          "lastDetectedAt": "2026-01-29T08:00:00Z",
          "detectionCount": 24
        },
        "comprehensions": {
          "firstDetectedAt": "2026-01-11T08:00:00Z",
          "lastDetectedAt": "2026-01-16T08:00:00Z",
          "detectionCount": 30
        },
        "classes-objects": {
          "firstDetectedAt": "2026-01-14T08:00:00Z",
          "lastDetectedAt": "2026-01-29T08:00:00Z",
          "detectionCount": 36
        },
        "read-write-files": {
          "firstDetectedAt": "2026-01-09T08:00:00Z",
          "lastDetectedAt": "2026-01-20T08:00:00Z",
          "detectionCount": 20
        },
        "context-managers": {
          "firstDetectedAt": "2026-01-09T08:00:00Z",
          "lastDetectedAt": "2026-01-19T08:00:00Z",
          "detectionCount": 22
        },
        "json-csv": {
          "firstDetectedAt": "2026-01-17T08:00:00Z",
          "lastDetectedAt": "2026-01-27T08:00:00Z",
          "detectionCount": 24
        },
        "try-except": {
          "firstDetectedAt": "2026-01-16T08:00:00Z",
          "lastDetectedAt": "2026-02-03T08:00:00Z",
          "detectionCount": 36
        },
        "custom-exceptions": {
          "firstDetectedAt": "2026-01-25T08:00:00Z",
          "lastDetectedAt": "2026-01-28T08:00:00Z",
          "detectionCount": 30
        },
        "exception-hierarchy": {
          "firstDetectedAt": "2026-01-13T08:00:00Z",
          "lastDetectedAt": "2026-01-31T08:00:00Z",
          "detectionCount": 25
        },
        "imports": {
          "firstDetectedAt": "2026-01-25T08:00:00Z",
          "lastDetectedAt": "2026-01-31T08:00:00Z",
          "detectionCount": 34
        },
        "packages": {
          "firstDetectedAt": "2026-01-24T08:00:00Z",
          "lastDetectedAt": "2026-02-06T08:00:00Z",
          "detectionCount": 31
        },
        "flask-django": {
          "firstDetectedAt": "2026-01-28T08:00:00Z",
          "lastDetectedAt": "2026-02-09T08:00:00Z",
          "detectionCount": 25
        },
        "routing-views": {
          "firstDetectedAt": "2026-01-21T08:00:00Z",
          "lastDetectedAt": "2026-01-31T08:00:00Z",
          "detectionCount": 30
        }
      }
    },
    "skill:SQL": {
      "roadmapVersion": "1.0",
      "firstUnlockedAt": "2026-01-06T08:00:00Z",
      "lastActivityAt": "2026-02-12T08:00:00Z",
      "completions": {
        "select-columns": {
          "firstDetectedAt": "2026-01-16T08:00:00Z",
          "lastDetectedAt": "2026-02-01T08:00:00Z",
          "detectionCount": 24
        },
        "distinct-values": {
          "firstDetectedAt": "2026-01-20T08:00:00Z",
          "lastDetectedAt": "2026-01-25T08:00:00Z",
          "detectionCount": 29
        },
        "arithmetic-expressions": {
          "firstDetectedAt": "2026-01-11T08:00:00Z",
          "lastDetectedAt": "2026-01-20T08:00:00Z",
          "detectionCount": 33
        },
        "where-clause": {
          "firstDetectedAt": "2026-01-16T08:00:00Z",
          "lastDetectedAt": "2026-01-27T08:00:00Z",
          "detectionCount": 37
        },
        "logical-operators": {
          "firstDetectedAt": "2026-01-12T08:00:00Z",
          "lastDetectedAt": "2026-01-14T08:00:00Z",
          "detectionCount": 38
        },
        "in-between-like": {
          "firstDetectedAt": "2026-01-12T08:00:00Z",
          "lastDetectedAt": "2026-02-04T08:00:00Z",
          "detectionCount": 23
        },
        "order-by": {
          "firstDetectedAt": "2026-01-23T08:00:00Z",
          "lastDetectedAt": "2026-02-06T08:00:00Z",
          "detectionCount": 32
        },
        "limit-offset": {
          "firstDetectedAt": "2026-01-08T08:00:00Z",
          "lastDetectedAt": "2026-01-10T08:00:00Z",
          "detectionCount": 38
        },
        "aggregate-functions": {
          "firstDetectedAt": "2026-01-24T08:00:00Z",
          "lastDetectedAt": "2026-02-08T08:00:00Z",
          "detectionCount": 37
        },
        "inner-join": {
          "firstDetectedAt": "2026-01-25T08:00:00Z",
          "lastDetectedAt": "2026-01-30T08:00:00Z",
          "detectionCount": 20
        },
        "outer-joins": {
          "firstDetectedAt": "2026-01-24T08:00:00Z",
          "lastDetectedAt": "2026-02-04T08:00:00Z",
          "detectionCount": 25
        },
        "self-cross-join": {
          "firstDetectedAt": "2026-01-14T08:00:00Z",
          "lastDetectedAt": "2026-02-05T08:00:00Z",
          "detectionCount": 37
        },
        "scalar-subquery": {
          "firstDetectedAt": "2026-01-22T08:00:00Z",
          "lastDetectedAt": "2026-01-27T08:00:00Z",
          "detectionCount": 24
        },
        "in-exists": {
          "firstDetectedAt": "2026-01-12T08:00:00Z",
          "lastDetectedAt": "2026-01-19T08:00:00Z",
          "detectionCount": 33
        },
        "subquery-in-from": {
          "firstDetectedAt": "2026-01-12T08:00:00Z",
          "lastDetectedAt": "2026-01-13T08:00:00Z",
          "detectionCount": 27
        },
        "with-clause": {
          "firstDetectedAt": "2026-01-16T08:00:00Z",
          "lastDetectedAt": "2026-02-10T08:00:00Z",
          "detectionCount": 35
        },
        "over-partition": {
          "firstDetectedAt": "2026-01-14T08:00:00Z",
          "lastDetectedAt": "2026-01-31T08:00:00Z",
          "detectionCount": 30
        },
        "rank-ntile": {
          "firstDetectedAt": "2026-01-06T08:00:00Z",
          "lastDetectedAt": "2026-01-08T08:00:00Z",
          "detectionCount": 23
        },
        "acid-basics": {
          "firstDetectedAt": "2026-01-09T08:00:00Z",
          "lastDetectedAt": "2026-02-12T08:00:00Z",
          "detectionCount": 22
        }
      }
    },
    "skill:PostgreSQL": {
      "roadmapVersion": "1.0",
      "firstUnlockedAt": "2026-01-06T08:00:00Z",
      "lastActivityAt": "2026-02-07T08:00:00Z",
      "completions": {
        "install-postgres": {
          "firstDetectedAt": "2026-01-28T08:00:00Z",
          "lastDetectedAt": "2026-02-06T08:00:00Z",
          "detectionCount": 10
        },
        "psql-connection": {
          "firstDetectedAt": "2026-01-26T08:00:00Z",
          "lastDetectedAt": "2026-02-07T08:00:00Z",
          "detectionCount": 18
        },
        "create-database": {
          "firstDetectedAt": "2026-01-23T08:00:00Z",
          "lastDetectedAt": "2026-02-04T08:00:00Z",
          "detectionCount": 13
        },
        "numeric-text": {
          "firstDetectedAt": "2026-01-09T08:00:00Z",
          "lastDetectedAt": "2026-01-23T08:00:00Z",
          "detectionCount": 18
        },
        "datetime-uuid": {
          "firstDetectedAt": "2026-01-13T08:00:00Z",
          "lastDetectedAt": "2026-01-17T08:00:00Z",
          "detectionCount": 17
        },
        "arrays-enums": {
          "firstDetectedAt": "2026-01-21T08:00:00Z",
          "lastDetectedAt": "2026-02-05T08:00:00Z",
          "detectionCount": 14
        },
        "create-tables": {
          "firstDetectedAt": "2026-01-20T08:00:00Z",
          "lastDetectedAt": "2026-01-23T08:00:00Z",
          "detectionCount": 8
        },
        "insert-select": {
          "firstDetectedAt": "2026-01-10T08:00:00Z",
          "lastDetectedAt": "2026-02-07T08:00:00Z",
          "detectionCount": 12
        },
        "btree-index": {
          "firstDetectedAt": "2026-01-17T08:00:00Z",
          "lastDetectedAt": "2026-02-04T08:00:00Z",
          "detectionCount": 16
        },
        "partial-gin": {
          "firstDetectedAt": "2026-01-23T08:00:00Z",
          "lastDetectedAt": "2026-02-05T08:00:00Z",
          "detectionCount": 18
        },
        "json-operators": {
          "firstDetectedAt": "2026-01-17T08:00:00Z",
          "lastDetectedAt": "2026-01-18T08:00:00Z",
          "detectionCount": 13
        },
        "jsonb-indexing": {
          "firstDetectedAt": "2026-01-06T08:00:00Z",
          "lastDetectedAt": "2026-01-30T08:00:00Z",
          "detectionCount": 12
        },
        "tsvector-tsquery": {
          "firstDetectedAt": "2026-01-10T08:00:00Z",
          "lastDetectedAt": "2026-02-04T08:00:00Z",
          "detectionCount": 14
        },
        "table-partitioning": {
          "firstDetectedAt": "2026-01-16T08:00:00Z",
          "lastDetectedAt": "2026-01-20T08:00:00Z",
          "detectionCount": 16
        },
        "partition-strategy": {
          "firstDetectedAt": "2026-01-17T08:00:00Z",
          "lastDetectedAt": "2026-01-19T08:00:00Z",
          "detectionCount": 14
        }
      }
    },
    "skill:MongoDB": {
      "roadmapVersion": "1.0",
      "firstUnlockedAt": "2026-01-08T08:00:00Z",
      "lastActivityAt": "2026-02-07T08:00:00Z",
      "completions": {
        "bson-structure": {
          "firstDetectedAt": "2026-01-13T08:00:00Z",
          "lastDetectedAt": "2026-01-24T08:00:00Z",
          "detectionCount": 8
        },
        "embedded-vs-references": {
          "firstDetectedAt": "2026-01-11T08:00:00Z",
          "lastDetectedAt": "2026-01-20T08:00:00Z",
          "detectionCount": 8
        },
        "collections-databases": {
          "firstDetectedAt": "2026-01-13T08:00:00Z",
          "lastDetectedAt": "2026-01-31T08:00:00Z",
          "detectionCount": 10
        },
        "insert-documents": {
          "firstDetectedAt": "2026-01-20T08:00:00Z",
          "lastDetectedAt": "2026-02-07T08:00:00Z",
          "detectionCount": 14
        },
        "find-replace": {
          "firstDetectedAt": "2026-01-09T08:00:00Z",
          "lastDetectedAt": "2026-01-23T08:00:00Z",
          "detectionCount": 15
        },
        "match-group": {
          "firstDetectedAt": "2026-01-08T08:00:00Z",
          "lastDetectedAt": "2026-01-11T08:00:00Z",
          "detectionCount": 11
        },
        "lookup-unwind": {
          "firstDetectedAt": "2026-01-13T08:00:00Z",
          "lastDetectedAt": "2026-02-04T08:00:00Z",
          "detectionCount": 17
        }
      }
    },
    "skill:Elasticsearch": {
      "roadmapVersion": "1.0",
      "firstUnlockedAt": "2026-01-07T08:00:00Z",
      "lastActivityAt": "2026-02-11T08:00:00Z",
      "completions": {
        "index-shard-concept": {
          "firstDetectedAt": "2026-01-27T08:00:00Z",
          "lastDetectedAt": "2026-02-10T08:00:00Z",
          "detectionCount": 14
        },
        "json-documents": {
          "firstDetectedAt": "2026-01-07T08:00:00Z",
          "lastDetectedAt": "2026-01-19T08:00:00Z",
          "detectionCount": 12
        },
        "index-get": {
          "firstDetectedAt": "2026-01-26T08:00:00Z",
          "lastDetectedAt": "2026-02-09T08:00:00Z",
          "detectionCount": 17
        },
        "update-delete": {
          "firstDetectedAt": "2026-01-17T08:00:00Z",
          "lastDetectedAt": "2026-02-04T08:00:00Z",
          "detectionCount": 13
        },
        "match-phrase": {
          "firstDetectedAt": "2026-01-19T08:00:00Z",
          "lastDetectedAt": "2026-01-29T08:00:00Z",
          "detectionCount": 13
        },
        "multi-match": {
          "firstDetectedAt": "2026-01-24T08:00:00Z",
          "lastDetectedAt": "2026-02-11T08:00:00Z",
          "detectionCount": 8
        }
      }
    },
    "skill:Docker": {
      "roadmapVersion": "1.0",
      "firstUnlockedAt": "2026-01-08T08:00:00Z",
      "lastActivityAt": "2026-02-05T08:00:00Z",
      "completions": {
        "understand-container-concept": {
          "firstDetectedAt": "2026-01-22T08:00:00Z",
          "lastDetectedAt": "2026-01-24T08:00:00Z",
          "detectionCount": 9
        },
        "resource-isolation": {
          "firstDetectedAt": "2026-01-25T08:00:00Z",
          "lastDetectedAt": "2026-01-30T08:00:00Z",
          "detectionCount": 11
        },
        "when-to-use-containers": {
          "firstDetectedAt": "2026-01-08T08:00:00Z",
          "lastDetectedAt": "2026-01-25T08:00:00Z",
          "detectionCount": 14
        },
        "create-dockerfile": {
          "firstDetectedAt": "2026-01-18T08:00:00Z",
          "lastDetectedAt": "2026-02-05T08:00:00Z",
          "detectionCount": 13
        },
        "build-images": {
          "firstDetectedAt": "2026-01-19T08:00:00Z",
          "lastDetectedAt": "2026-01-23T08:00:00Z",
          "detectionCount": 8
        },
        "image-layers": {
          "firstDetectedAt": "2026-01-15T08:00:00Z",
          "lastDetectedAt": "2026-02-02T08:00:00Z",
          "detectionCount": 15
        },
        "volume-types": {
          "firstDetectedAt": "2026-01-19T08:00:00Z",
          "lastDetectedAt": "2026-01-23T08:00:00Z",
          "detectionCount": 10
        },
        "persist-data": {
          "firstDetectedAt": "2026-01-17T08:00:00Z",
          "lastDetectedAt": "2026-01-31T08:00:00Z",
          "detectionCount": 13
        },
        "volume-inspect": {
          "firstDetectedAt": "2026-01-13T08:00:00Z",
          "lastDetectedAt": "2026-02-05T08:00:00Z",
          "detectionCount": 10
        }
      }
    },
    "skill:AWS": {
      "roadmapVersion": "1.0",
      "firstUnlockedAt": "2026-01-10T08:00:00Z",
      "lastActivityAt": "2026-02-07T08:00:00Z",
      "completions": {
        "users-groups": {
          "firstDetectedAt": "2026-01-19T08:00:00Z",
          "lastDetectedAt": "2026-01-25T08:00:00Z",
          "detectionCount": 11
        },
        "roles": {
          "firstDetectedAt": "2026-01-12T08:00:00Z",
          "lastDetectedAt": "2026-01-12T08:00:00Z",
          "detectionCount": 14
        },
        "policy-json": {
          "firstDetectedAt": "2026-01-16T08:00:00Z",
          "lastDetectedAt": "2026-02-07T08:00:00Z",
          "detectionCount": 15
        },
        "best-practices-iam": {
          "firstDetectedAt": "2026-01-15T08:00:00Z",
          "lastDetectedAt": "2026-01-28T08:00:00Z",
          "detectionCount": 14
        },
        "launch-instance": {
          "firstDetectedAt": "2026-01-10T08:00:00Z",
          "lastDetectedAt": "2026-01-31T08:00:00Z",
          "detectionCount": 14
        },
        "create-rds-instance": {
          "firstDetectedAt": "2026-01-13T08:00:00Z",
          "lastDetectedAt": "2026-01-27T08:00:00Z",
          "detectionCount": 13
        },
        "multi-az": {
          "firstDetectedAt": "2026-01-17T08:00:00Z",
          "lastDetectedAt": "2026-01-27T08:00:00Z",
          "detectionCount": 14
        }
      }
    },
    "skill:Git and GitHub": {
      "roadmapVersion": "1.0",
      "firstUnlockedAt": "2026-01-07T08:00:00Z",
      "lastActivityAt": "2026-02-07T08:00:00Z",
      "completions": {
        "git-init": {
          "firstDetectedAt": "2026-01-09T08:00:00Z",
          "lastDetectedAt": "2026-02-06T08:00:00Z",
          "detectionCount": 9
        },
        "add-commit": {
          "firstDetectedAt": "2026-01-26T08:00:00Z",
          "lastDetectedAt": "2026-02-05T08:00:00Z",
          "detectionCount": 11
        },
        "status-log": {
          "firstDetectedAt": "2026-01-21T08:00:00Z",
          "lastDetectedAt": "2026-01-31T08:00:00Z",
          "detectionCount": 15
        },
        "diff": {
          "firstDetectedAt": "2026-01-07T08:00:00Z",
          "lastDetectedAt": "2026-02-05T08:00:00Z",
          "detectionCount": 13
        },
        "create-branch": {
          "firstDetectedAt": "2026-01-28T08:00:00Z",
          "lastDetectedAt": "2026-01-31T08:00:00Z",
          "detectionCount": 16
        },
        "merge-branch": {
          "firstDetectedAt": "2026-01-23T08:00:00Z",
          "lastDetectedAt": "2026-02-07T08:00:00Z",
          "detectionCount": 18
        },
        "create-pr": {
          "firstDetectedAt": "2026-01-18T08:00:00Z",
          "lastDetectedAt": "2026-02-07T08:00:00Z",
          "detectionCount": 13
        },
        "review-pr": {
          "firstDetectedAt": "2026-01-08T08:00:00Z",
          "lastDetectedAt": "2026-01-21T08:00:00Z",
          "detectionCount": 12
        },
        "merge-strategies": {
          "firstDetectedAt": "2026-01-21T08:00:00Z",
          "lastDetectedAt": "2026-01-26T08:00:00Z",
          "detectionCount": 9
        }
      }
    }
  }
}