{
  "userId": "eng-003",
  "name": "Carol Liu",
  "createdAt": "2026-01-05T00:00:00Z",
  "lastScannedAt": "2026-02-13T08:00:00Z",
  "roadmaps": {
    "role:Frontend": {
      "roadmapVersion": "1.0",
      "firstUnlockedAt": "2026-01-07T08:00:00Z",
      "lastActivityAt": "2026-02-13T08:00:00Z",
      "completions": {
        "how-internet-works": {"firstDetectedAt": "2026-01-07T08:00:00Z", "lastDetectedAt": "2026-02-10T08:00:00Z", "detectionCount": 18},
        "http-https": {"firstDetectedAt": "2026-01-07T08:00:00Z", "lastDetectedAt": "2026-02-13T08:00:00Z", "detectionCount": 28},
        "dns-hosting": {"firstDetectedAt": "2026-01-09T08:00:00Z", "lastDetectedAt": "2026-02-05T08:00:00Z", "detectionCount": 8},
        "semantic-html": {"firstDetectedAt": "2026-01-07T08:00:00Z", "lastDetectedAt": "2026-02-13T08:00:00Z", "detectionCount": 34},
        "forms-validation": {"firstDetectedAt": "2026-01-08T08:00:00Z", "lastDetectedAt": "2026-02-12T08:00:00Z", "detectionCount": 26},
        "seo-basics": {"firstDetectedAt": "2026-01-12T08:00:00Z", "lastDetectedAt": "2026-02-08T08:00:00Z", "detectionCount": 12},
        "layout": {"firstDetectedAt": "2026-01-07T08:00:00Z", "lastDetectedAt": "2026-02-13T08:00:00Z", "detectionCount": 36},
        "animations": {"firstDetectedAt": "2026-01-10T08:00:00Z", "lastDetectedAt": "2026-02-11T08:00:00Z", "detectionCount": 22},
        "css-variables": {"firstDetectedAt": "2026-01-09T08:00:00Z", "lastDetectedAt": "2026-02-13T08:00:00Z", "detectionCount": 28},
        "core-js": {"firstDetectedAt": "2026-01-07T08:00:00Z", "lastDetectedAt": "2026-02-13T08:00:00Z", "detectionCount": 38},
        "es6-plus": {"firstDetectedAt": "2026-01-07T08:00:00Z", "lastDetectedAt": "2026-02-13T08:00:00Z", "detectionCount": 36},
        "async": {"firstDetectedAt": "2026-01-08T08:00:00Z", "lastDetectedAt": "2026-02-13T08:00:00Z", "detectionCount": 32},
        "types-interfaces": {"firstDetectedAt": "2026-01-12T08:00:00Z", "lastDetectedAt": "2026-02-13T08:00:00Z", "detectionCount": 28},
        "generics": {"firstDetectedAt": "2026-01-15T08:00:00Z", "lastDetectedAt": "2026-02-10T08:00:00Z", "detectionCount": 14},
        "ts-config": {"firstDetectedAt": "2026-01-14T08:00:00Z", "lastDetectedAt": "2026-02-08T08:00:00Z", "detectionCount": 10},
        "react": {"firstDetectedAt": "2026-01-07T08:00:00Z", "lastDetectedAt": "2026-02-13T08:00:00Z", "detectionCount": 38},
        "tailwind": {"firstDetectedAt": "2026-01-08T08:00:00Z", "lastDetectedAt": "2026-02-13T08:00:00Z", "detectionCount": 34},
        "css-modules": {"firstDetectedAt": "2026-01-18T08:00:00Z", "lastDetectedAt": "2026-02-10T08:00:00Z", "detectionCount": 12},
        "vite": {"firstDetectedAt": "2026-01-08T08:00:00Z", "lastDetectedAt": "2026-02-13T08:00:00Z", "detectionCount": 30},
        "unit-testing": {"firstDetectedAt": "2026-01-20T08:00:00Z", "lastDetectedAt": "2026-02-12T08:00:00Z", "detectionCount": 18},
        "e2e": {"firstDetectedAt": "2026-01-25T08:00:00Z", "lastDetectedAt": "2026-02-08T08:00:00Z", "detectionCount": 8},
        "nextjs": {"firstDetectedAt": "2026-01-22T08:00:00Z", "lastDetectedAt": "2026-02-13T08:00:00Z", "detectionCount": 24},
        "client-state": {"firstDetectedAt": "2026-01-28T08:00:00Z", "lastDetectedAt": "2026-02-12T08:00:00Z", "detectionCount": 14},
        "core-web-vitals": {"firstDetectedAt": "2026-02-01T08:00:00Z", "lastDetectedAt": "2026-02-10T08:00:00Z", "detectionCount": 5},
        "ai-coding": {"firstDetectedAt": "2026-02-05T08:00:00Z", "lastDetectedAt": "2026-02-13T08:00:00Z", "detectionCount": 6}
      }
    },
    "skill:JavaScript": {
      "roadmapVersion": "1.0",
      "firstUnlockedAt": "2026-01-06T08:00:00Z",
      "lastActivityAt": "2026-02-13T08:00:00Z",
      "completions": {
        "variables-types": {"firstDetectedAt": "2026-01-06T08:00:00Z", "lastDetectedAt": "2026-02-13T08:00:00Z", "detectionCount": 36},
        "control-flow": {"firstDetectedAt": "2026-01-06T08:00:00Z", "lastDetectedAt": "2026-02-13T08:00:00Z", "detectionCount": 35},
        "functions": {"firstDetectedAt": "2026-01-07T08:00:00Z", "lastDetectedAt": "2026-02-13T08:00:00Z", "detectionCount": 34},
        "arrays-objects": {"firstDetectedAt": "2026-01-07T08:00:00Z", "lastDetectedAt": "2026-02-12T08:00:00Z", "detectionCount": 32},
        "selecting-elements": {"firstDetectedAt": "2026-01-08T08:00:00Z", "lastDetectedAt": "2026-02-12T08:00:00Z", "detectionCount": 28},
        "modifying-dom": {"firstDetectedAt": "2026-01-08T08:00:00Z", "lastDetectedAt": "2026-02-13T08:00:00Z", "detectionCount": 30},
        "event-listeners": {"firstDetectedAt": "2026-01-09T08:00:00Z", "lastDetectedAt": "2026-02-12T08:00:00Z", "detectionCount": 28},
        "let-const-arrow": {"firstDetectedAt": "2026-01-07T08:00:00Z", "lastDetectedAt": "2026-02-13T08:00:00Z", "detectionCount": 35},
        "destructuring-spread": {"firstDetectedAt": "2026-01-09T08:00:00Z", "lastDetectedAt": "2026-02-12T08:00:00Z", "detectionCount": 26},
        "template-literals": {"firstDetectedAt": "2026-01-10T08:00:00Z", "lastDetectedAt": "2026-02-11T08:00:00Z", "detectionCount": 24},
        "callbacks-promises": {"firstDetectedAt": "2026-01-11T08:00:00Z", "lastDetectedAt": "2026-02-12T08:00:00Z", "detectionCount": 22},
        "async-await": {"firstDetectedAt": "2026-01-11T08:00:00Z", "lastDetectedAt": "2026-02-13T08:00:00Z", "detectionCount": 26},
        "fetch-api": {"firstDetectedAt": "2026-01-12T08:00:00Z", "lastDetectedAt": "2026-02-11T08:00:00Z", "detectionCount": 20},
        "closures": {"firstDetectedAt": "2026-01-14T08:00:00Z", "lastDetectedAt": "2026-02-08T08:00:00Z", "detectionCount": 12},
        "prototype-chain": {"firstDetectedAt": "2026-01-18T08:00:00Z", "lastDetectedAt": "2026-02-05T08:00:00Z", "detectionCount": 6},
        "try-catch": {"firstDetectedAt": "2026-01-16T08:00:00Z", "lastDetectedAt": "2026-02-10T08:00:00Z", "detectionCount": 14},
        "jest-basics": {"firstDetectedAt": "2026-01-20T08:00:00Z", "lastDetectedAt": "2026-02-12T08:00:00Z", "detectionCount": 16},
        "design-patterns": {"firstDetectedAt": "2026-02-05T08:00:00Z", "lastDetectedAt": "2026-02-12T08:00:00Z", "detectionCount": 3}
      }
    },
    "skill:TypeScript": {
      "roadmapVersion": "1.0",
      "firstUnlockedAt": "2026-01-11T08:00:00Z",
      "lastActivityAt": "2026-02-12T08:00:00Z",
      "completions": {
        "primitive-types": {"firstDetectedAt": "2026-01-11T08:00:00Z", "lastDetectedAt": "2026-02-12T08:00:00Z", "detectionCount": 28},
        "type-inference": {"firstDetectedAt": "2026-01-12T08:00:00Z", "lastDetectedAt": "2026-02-11T08:00:00Z", "detectionCount": 24},
        "strict-mode": {"firstDetectedAt": "2026-01-14T08:00:00Z", "lastDetectedAt": "2026-02-08T08:00:00Z", "detectionCount": 12},
        "interface-definition": {"firstDetectedAt": "2026-01-12T08:00:00Z", "lastDetectedAt": "2026-02-12T08:00:00Z", "detectionCount": 26},
        "optional-properties": {"firstDetectedAt": "2026-01-14T08:00:00Z", "lastDetectedAt": "2026-02-10T08:00:00Z", "detectionCount": 16},
        "extending-interfaces": {"firstDetectedAt": "2026-01-16T08:00:00Z", "lastDetectedAt": "2026-02-08T08:00:00Z", "detectionCount": 12},
        "generic-functions": {"firstDetectedAt": "2026-01-18T08:00:00Z", "lastDetectedAt": "2026-02-11T08:00:00Z", "detectionCount": 18},
        "generic-interfaces": {"firstDetectedAt": "2026-01-20T08:00:00Z", "lastDetectedAt": "2026-02-05T08:00:00Z", "detectionCount": 8},
        "numeric-string-enums": {"firstDetectedAt": "2026-01-22T08:00:00Z", "lastDetectedAt": "2026-02-10T08:00:00Z", "detectionCount": 10},
        "partial-required": {"firstDetectedAt": "2026-01-25T08:00:00Z", "lastDetectedAt": "2026-02-08T08:00:00Z", "detectionCount": 8},
        "union-intersection": {"firstDetectedAt": "2026-01-28T08:00:00Z", "lastDetectedAt": "2026-02-10T08:00:00Z", "detectionCount": 10},
        "type-guards": {"firstDetectedAt": "2026-02-01T08:00:00Z", "lastDetectedAt": "2026-02-12T08:00:00Z", "detectionCount": 8},
        "tsconfig": {"firstDetectedAt": "2026-01-20T08:00:00Z", "lastDetectedAt": "2026-02-12T08:00:00Z", "detectionCount": 14},
        "react-types": {"firstDetectedAt": "2026-01-25T08:00:00Z", "lastDetectedAt": "2026-02-12T08:00:00Z", "detectionCount": 16}
      }
    },
    "skill:React": {
      "roadmapVersion": "1.0",
      "firstUnlockedAt": "2026-01-10T08:00:00Z",
      "lastActivityAt": "2026-02-13T08:00:00Z",
      "completions": {
        "jsx-syntax": {"firstDetectedAt": "2026-01-10T08:00:00Z", "lastDetectedAt": "2026-02-13T08:00:00Z", "detectionCount": 35},
        "jsx-attributes": {"firstDetectedAt": "2026-01-10T08:00:00Z", "lastDetectedAt": "2026-02-12T08:00:00Z", "detectionCount": 32},
        "jsx-children": {"firstDetectedAt": "2026-01-11T08:00:00Z", "lastDetectedAt": "2026-02-13T08:00:00Z", "detectionCount": 30},
        "jsx-conditional": {"firstDetectedAt": "2026-01-12T08:00:00Z", "lastDetectedAt": "2026-02-12T08:00:00Z", "detectionCount": 28},
        "function-components": {"firstDetectedAt": "2026-01-10T08:00:00Z", "lastDetectedAt": "2026-02-13T08:00:00Z", "detectionCount": 36},
        "component-composition": {"firstDetectedAt": "2026-01-11T08:00:00Z", "lastDetectedAt": "2026-02-12T08:00:00Z", "detectionCount": 30},
        "component-reuse": {"firstDetectedAt": "2026-01-12T08:00:00Z", "lastDetectedAt": "2026-02-11T08:00:00Z", "detectionCount": 26},
        "props-passing": {"firstDetectedAt": "2026-01-11T08:00:00Z", "lastDetectedAt": "2026-02-13T08:00:00Z", "detectionCount": 34},
        "state-basics": {"firstDetectedAt": "2026-01-12T08:00:00Z", "lastDetectedAt": "2026-02-13T08:00:00Z", "detectionCount": 35},
        "lifting-state": {"firstDetectedAt": "2026-01-14T08:00:00Z", "lastDetectedAt": "2026-02-12T08:00:00Z", "detectionCount": 24},
        "immutable-updates": {"firstDetectedAt": "2026-01-15T08:00:00Z", "lastDetectedAt": "2026-02-10T08:00:00Z", "detectionCount": 20},
        "useeffect-deps": {"firstDetectedAt": "2026-01-16T08:00:00Z", "lastDetectedAt": "2026-02-13T08:00:00Z", "detectionCount": 28},
        "useeffect-cleanup": {"firstDetectedAt": "2026-01-18T08:00:00Z", "lastDetectedAt": "2026-02-11T08:00:00Z", "detectionCount": 18},
        "custom-hooks": {"firstDetectedAt": "2026-01-20T08:00:00Z", "lastDetectedAt": "2026-02-12T08:00:00Z", "detectionCount": 20},
        "create-context": {"firstDetectedAt": "2026-01-22T08:00:00Z", "lastDetectedAt": "2026-02-10T08:00:00Z", "detectionCount": 14},
        "use-context": {"firstDetectedAt": "2026-01-22T08:00:00Z", "lastDetectedAt": "2026-02-12T08:00:00Z", "detectionCount": 18},
        "react-router-setup": {"firstDetectedAt": "2026-01-25T08:00:00Z", "lastDetectedAt": "2026-02-12T08:00:00Z", "detectionCount": 20},
        "controlled-inputs": {"firstDetectedAt": "2026-01-28T08:00:00Z", "lastDetectedAt": "2026-02-11T08:00:00Z", "detectionCount": 16},
        "jest-setup": {"firstDetectedAt": "2026-02-01T08:00:00Z", "lastDetectedAt": "2026-02-12T08:00:00Z", "detectionCount": 10},
        "react-memo": {"firstDetectedAt": "2026-02-05T08:00:00Z", "lastDetectedAt": "2026-02-12T08:00:00Z", "detectionCount": 6}
      }
    },
    "skill:Next.js": {
      "roadmapVersion": "1.0",
      "firstUnlockedAt": "2026-01-18T08:00:00Z",
      "lastActivityAt": "2026-02-12T08:00:00Z",
      "completions": {
        "pages-router": {"firstDetectedAt": "2026-01-18T08:00:00Z", "lastDetectedAt": "2026-02-08T08:00:00Z", "detectionCount": 12},
        "app-router-structure": {"firstDetectedAt": "2026-01-20T08:00:00Z", "lastDetectedAt": "2026-02-12T08:00:00Z", "detectionCount": 22},
        "layout-template": {"firstDetectedAt": "2026-01-20T08:00:00Z", "lastDetectedAt": "2026-02-11T08:00:00Z", "detectionCount": 18},
        "loading-error": {"firstDetectedAt": "2026-01-22T08:00:00Z", "lastDetectedAt": "2026-02-08T08:00:00Z", "detectionCount": 8},
        "server-components-default": {"firstDetectedAt": "2026-01-22T08:00:00Z", "lastDetectedAt": "2026-02-12T08:00:00Z", "detectionCount": 20},
        "static-generation": {"firstDetectedAt": "2026-01-25T08:00:00Z", "lastDetectedAt": "2026-02-05T08:00:00Z", "detectionCount": 8},
        "dynamic-rendering": {"firstDetectedAt": "2026-01-25T08:00:00Z", "lastDetectedAt": "2026-02-10T08:00:00Z", "detectionCount": 10},
        "fetch-server": {"firstDetectedAt": "2026-01-28T08:00:00Z", "lastDetectedAt": "2026-02-12T08:00:00Z", "detectionCount": 16},
        "route-handlers": {"firstDetectedAt": "2026-02-01T08:00:00Z", "lastDetectedAt": "2026-02-10T08:00:00Z", "detectionCount": 8},
        "middleware-file": {"firstDetectedAt": "2026-02-05T08:00:00Z", "lastDetectedAt": "2026-02-12T08:00:00Z", "detectionCount": 6}
      }
    },
    "skill:HTML": {
      "roadmapVersion": "1.0",
      "firstUnlockedAt": "2026-01-06T08:00:00Z",
      "lastActivityAt": "2026-02-13T08:00:00Z",
      "completions": {
        "doctype-and-html": {"firstDetectedAt": "2026-01-06T08:00:00Z", "lastDetectedAt": "2026-02-12T08:00:00Z", "detectionCount": 30},
        "head-meta-charset": {"firstDetectedAt": "2026-01-06T08:00:00Z", "lastDetectedAt": "2026-02-13T08:00:00Z", "detectionCount": 32},
        "body-structure": {"firstDetectedAt": "2026-01-07T08:00:00Z", "lastDetectedAt": "2026-02-12T08:00:00Z", "detectionCount": 28},
        "header-nav-footer": {"firstDetectedAt": "2026-01-07T08:00:00Z", "lastDetectedAt": "2026-02-13T08:00:00Z", "detectionCount": 34},
        "article-section": {"firstDetectedAt": "2026-01-09T08:00:00Z", "lastDetectedAt": "2026-02-11T08:00:00Z", "detectionCount": 24},
        "form-input-types": {"firstDetectedAt": "2026-01-08T08:00:00Z", "lastDetectedAt": "2026-02-12T08:00:00Z", "detectionCount": 26},
        "labels-placeholders": {"firstDetectedAt": "2026-01-09T08:00:00Z", "lastDetectedAt": "2026-02-10T08:00:00Z", "detectionCount": 20},
        "html5-validation": {"firstDetectedAt": "2026-01-12T08:00:00Z", "lastDetectedAt": "2026-02-08T08:00:00Z", "detectionCount": 12},
        "img-attributes": {"firstDetectedAt": "2026-01-14T08:00:00Z", "lastDetectedAt": "2026-02-10T08:00:00Z", "detectionCount": 14},
        "aria-roles": {"firstDetectedAt": "2026-01-18T08:00:00Z", "lastDetectedAt": "2026-02-05T08:00:00Z", "detectionCount": 8},
        "heading-hierarchy": {"firstDetectedAt": "2026-01-16T08:00:00Z", "lastDetectedAt": "2026-02-10T08:00:00Z", "detectionCount": 12},
        "alt-text": {"firstDetectedAt": "2026-01-20T08:00:00Z", "lastDetectedAt": "2026-02-08T08:00:00Z", "detectionCount": 10}
      }
    },
    "skill:CSS": {
      "roadmapVersion": "1.0",
      "firstUnlockedAt": "2026-01-06T08:00:00Z",
      "lastActivityAt": "2026-02-13T08:00:00Z",
      "completions": {
        "basic-selectors": {"firstDetectedAt": "2026-01-06T08:00:00Z", "lastDetectedAt": "2026-02-13T08:00:00Z", "detectionCount": 35},
        "combinators": {"firstDetectedAt": "2026-01-07T08:00:00Z", "lastDetectedAt": "2026-02-12T08:00:00Z", "detectionCount": 30},
        "pseudo-classes": {"firstDetectedAt": "2026-01-07T08:00:00Z", "lastDetectedAt": "2026-02-13T08:00:00Z", "detectionCount": 32},
        "specificity-cascade": {"firstDetectedAt": "2026-01-08T08:00:00Z", "lastDetectedAt": "2026-02-10T08:00:00Z", "detectionCount": 22},
        "content-padding-border": {"firstDetectedAt": "2026-01-06T08:00:00Z", "lastDetectedAt": "2026-02-13T08:00:00Z", "detectionCount": 34},
        "box-sizing": {"firstDetectedAt": "2026-01-08T08:00:00Z", "lastDetectedAt": "2026-02-12T08:00:00Z", "detectionCount": 26},
        "flex-container": {"firstDetectedAt": "2026-01-07T08:00:00Z", "lastDetectedAt": "2026-02-13T08:00:00Z", "detectionCount": 36},
        "flex-wrap-align": {"firstDetectedAt": "2026-01-08T08:00:00Z", "lastDetectedAt": "2026-02-12T08:00:00Z", "detectionCount": 30},
        "grid-template": {"firstDetectedAt": "2026-01-10T08:00:00Z", "lastDetectedAt": "2026-02-12T08:00:00Z", "detectionCount": 26},
        "media-queries": {"firstDetectedAt": "2026-01-12T08:00:00Z", "lastDetectedAt": "2026-02-13T08:00:00Z", "detectionCount": 24},
        "transitions": {"firstDetectedAt": "2026-01-14T08:00:00Z", "lastDetectedAt": "2026-02-11T08:00:00Z", "detectionCount": 18},
        "keyframes": {"firstDetectedAt": "2026-01-18T08:00:00Z", "lastDetectedAt": "2026-02-08T08:00:00Z", "detectionCount": 10},
        "custom-properties": {"firstDetectedAt": "2026-01-16T08:00:00Z", "lastDetectedAt": "2026-02-12T08:00:00Z", "detectionCount": 20},
        "container-queries": {"firstDetectedAt": "2026-02-05T08:00:00Z", "lastDetectedAt": "2026-02-12T08:00:00Z", "detectionCount": 4}
      }
    },
    "skill:Git and GitHub": {
      "roadmapVersion": "1.0",
      "firstUnlockedAt": "2026-01-07T08:00:00Z",
      "lastActivityAt": "2026-02-13T08:00:00Z",
      "completions": {
        "git-init": {"firstDetectedAt": "2026-01-07T08:00:00Z", "lastDetectedAt": "2026-02-12T08:00:00Z", "detectionCount": 28},
        "add-commit": {"firstDetectedAt": "2026-01-07T08:00:00Z", "lastDetectedAt": "2026-02-13T08:00:00Z", "detectionCount": 32},
        "status-log": {"firstDetectedAt": "2026-01-08T08:00:00Z", "lastDetectedAt": "2026-02-13T08:00:00Z", "detectionCount": 30},
        "diff": {"firstDetectedAt": "2026-01-08T08:00:00Z", "lastDetectedAt": "2026-02-11T08:00:00Z", "detectionCount": 24},
        "create-branch": {"firstDetectedAt": "2026-01-09T08:00:00Z", "lastDetectedAt": "2026-02-12T08:00:00Z", "detectionCount": 22},
        "merge-branch": {"firstDetectedAt": "2026-01-10T08:00:00Z", "lastDetectedAt": "2026-02-10T08:00:00Z", "detectionCount": 16},
        "add-remote": {"firstDetectedAt": "2026-01-09T08:00:00Z", "lastDetectedAt": "2026-02-13T08:00:00Z", "detectionCount": 28},
        "push-pull": {"firstDetectedAt": "2026-01-09T08:00:00Z", "lastDetectedAt": "2026-02-13T08:00:00Z", "detectionCount": 30},
        "create-pr": {"firstDetectedAt": "2026-01-14T08:00:00Z", "lastDetectedAt": "2026-02-12T08:00:00Z", "detectionCount": 18},
        "review-pr": {"firstDetectedAt": "2026-01-16T08:00:00Z", "lastDetectedAt": "2026-02-08T08:00:00Z", "detectionCount": 12},
        "resolve-conflicts": {"firstDetectedAt": "2026-01-22T08:00:00Z", "lastDetectedAt": "2026-02-05T08:00:00Z", "detectionCount": 6}
      }
    }
  }
}
